{
  "timestamp": "2026-04-18T03:18:50.313893",
  "winning_strategy": "Vol-0.7\u00d7",
  "test_auc": 0.7114621489621489,
  "test_f1": 0.37362637362637363,
  "train_auc": 0.9264099244680626,
  "crash_rate": 0.20575842696629212,
  "all_results": [
    {
      "strategy": "Vol-0.5\u00d7",
      "train_rate": 0.3693820224719101,
      "test_rate": 0.2689655172413793,
      "train_auc": 0.8707743019976797,
      "valid_auc": 0.8385638297872341,
      "test_auc": 0.672048863086599,
      "test_f1": 0.4549763033175355,
      "n_trees": 17,
      "status": "ok"
    },
    {
      "strategy": "Vol-0.7\u00d7",
      "train_rate": 0.20575842696629212,
      "test_rate": 0.19310344827586207,
      "train_auc": 0.9264099244680626,
      "valid_auc": 0.7743533296642817,
      "test_auc": 0.7114621489621489,
      "test_f1": 0.37362637362637363,
      "n_trees": 51,
      "status": "ok"
    },
    {
      "strategy": "Vol-0.85\u00d7",
      "train_rate": 0.12851123595505617,
      "test_rate": 0.14482758620689656,
      "train_auc": 0.9891899270375115,
      "valid_auc": 0.6905248807089298,
      "test_auc": 0.642089093701997,
      "test_f1": 0.2459016393442623,
      "n_trees": 148,
      "status": "ok"
    },
    {
      "strategy": "Vol-1.0\u00d7",
      "train_rate": 0.09129213483146068,
      "test_rate": 0.10344827586206896,
      "train_auc": 0.959338960884556,
      "valid_auc": 0.6428571428571429,
      "test_auc": 0.6187820512820513,
      "test_f1": 0.27522935779816515,
      "n_trees": 31,
      "status": "ok"
    },
    {
      "strategy": "Vol-1.2\u00d7",
      "train_rate": 0.056179775280898875,
      "test_rate": 0.06896551724137931,
      "train_auc": 0.9692196800595239,
      "valid_auc": 0.5813953488372093,
      "test_auc": 0.4733333333333334,
      "test_f1": 0.057971014492753624,
      "n_trees": 13,
      "status": "ok"
    },
    {
      "strategy": "Pct-15%/yr",
      "train_rate": 0.1499312242090784,
      "test_rate": 0.19865319865319866,
      "train_auc": 0.9782444107954039,
      "valid_auc": 0.7938856015779092,
      "test_auc": 0.5764848312206239,
      "test_f1": 0.25,
      "n_trees": 109,
      "status": "ok"
    },
    {
      "strategy": "Pct-20%/yr",
      "train_rate": 0.19944979367262725,
      "test_rate": 0.24915824915824916,
      "train_auc": 0.8730062803649722,
      "valid_auc": 0.8880766731643925,
      "test_auc": 0.6422251848260817,
      "test_f1": 0.41346153846153844,
      "n_trees": 8,
      "status": "ok"
    },
    {
      "strategy": "Pct-25%/yr",
      "train_rate": 0.25034387895460797,
      "test_rate": 0.2996632996632997,
      "train_auc": 0.9056684141546526,
      "valid_auc": 0.8699813258636789,
      "test_auc": 0.6624621866897148,
      "test_f1": 0.4788732394366197,
      "n_trees": 27,
      "status": "ok"
    },
    {
      "strategy": "Abs-5%",
      "train_rate": 0.42916093535075656,
      "test_rate": 0.2620689655172414,
      "train_auc": 0.9313339898053754,
      "valid_auc": 0.8395061728395061,
      "test_auc": 0.6946015740285294,
      "test_f1": 0.4835164835164835,
      "n_trees": 83,
      "status": "ok"
    },
    {
      "strategy": "Abs-7%",
      "train_rate": 0.30261348005502064,
      "test_rate": 0.1793103448275862,
      "train_auc": 0.82730410615026,
      "valid_auc": 0.7228682170542635,
      "test_auc": 0.6578458306399483,
      "test_f1": 0.3114754098360656,
      "n_trees": 1,
      "status": "ok"
    },
    {
      "strategy": "Abs-10%",
      "train_rate": 0.16781292984869325,
      "test_rate": 0.07931034482758621,
      "train_auc": 0.9159243327462403,
      "valid_auc": 0.6029624277456647,
      "test_auc": 0.6437876567334311,
      "test_f1": 0.125,
      "n_trees": 3,
      "status": "ok"
    }
  ],
  "feature_list": [
    "modal_price",
    "arrival_qty",
    "min_price",
    "max_price",
    "hingoli_price",
    "latur_price",
    "parbhani_price",
    "surrounding_price",
    "usd_inr",
    "cbot_close",
    "cbot_weekly_change",
    "price_spread_ratio",
    "price_velocity",
    "price_trend_30d",
    "arrival_ratio",
    "price_vs_7d_avg",
    "rain_7d_sum",
    "temp_7d_avg",
    "is_raining_today",
    "weather_shock_flag",
    "month",
    "day_of_week",
    "year_norm",
    "price_wave_lag_score",
    "acceleration",
    "distance_from_min",
    "trend_strength",
    "drawdown_7",
    "cbot_price_inr",
    "cbot_7day_trend",
    "days_from_harvest_start",
    "msp_gap"
  ]
}